{
    "body": "\n \n \n \n \n \n \n \n \n \n \n \n \n \n About this mailing: \nYou are receiving this e-mail because you subscribed to MSN Featured Offers. If you do not wish to receive this MSN Featured Offers e-mail, please click the \"Unsubscribe\" link below. This will not unsubscribe \nyou from e-mail communications from third-party advertisers that may appear in MSN Feature Offers. This shall not constitute an offer by MSN. MSN shall not be responsible or liable for the advertisers' content nor any of the goods or service \n advertised. Prices and item availability subject to change without notice. \n \n ©2008 | Unsubscribe | More Newsletters | Privacy \n \n \n \n \n \n \n \n \n \n \n \n \n \n \n \n \n \n \n \n", 
    "to": [
        "hibody@csmining.org"
    ], 
    "is_spam": true, 
    "from": "hibody@csmining.org", 
    "subject": "[SPAM]  Dear hibody@csmining.org 27.6.2009 80% 0FF on Pfizer."
}