{
    "body": "Update: High Quality, Low Cost \n \n \n \n \n \n \n \n \n \n \n     \n \n \n \n \n \n \n \n \n \n   \n \n \n \n \n In the October 1, 2009 Issue: \n \n \n \n \n \n \n \n \n \n News \n \n \n \n \n \n \n \n \n \n \n READ THE FULL ARTICLE \n \n \n \n \n \n \n \n \n \n \n \n \n \n \n \n \n \n \n Subscribe  |  Change email address  |  Online Version  |  Mobile Version \n \n \n \n \n \n \n \n \n \n ABOUT OUR NEWSLETTER \n \n To unsubscribe \n click here. \n \n To subscribe, visit our e-newsletter subscription center at \n \nthis link \n \n \n Read the \nPenton Media Privacy Policy. \n Penton Media | 249 W. 17th Street | New York, NY 10011 \n \nCopyright 2009, Penton Media. All rights reserved. This article is protected by \nUnited States copyright and other intellectual property laws and may not be \nreproduced, rewritten, distributed, re-disseminated, transmitted, displayed, \npublished or broadcast, directly or indirectly, in any medium without the prior \nwritten permission of Penton Media. \n \n \n \n \n \n \n \n \n \n \n \n", 
    "to": [
        "hibody@csmining.org"
    ], 
    "is_spam": true, 
    "from": "\"Lashonda Millott\" <hibody@csmining.org>", 
    "subject": "[SPAM]  Video problems"
}