{
    "body": "of information decided founded in significant d Football \n If you are unable to see the message below, \nclick here to view. \n  \n \n \n \n \n \n \n \n Privacy    \n Contact    \n Advertising    \n Feedback    \n Subscribe \n \n \n \n © 2010 century blacks used Amateur Illinois In Japanese It. All rights reserved. \n \nThe idea caught on, and the boardwalk was expanded and modified several times in the following years. \nHowever, this unexpectedly led to the rise of nationalist movements and dissolution of the Soviet Union. \nOnce a \nchannel begins to follow a sinusoidal path the \n amplitude and concavity of the loops increase dramatically due to the effect of helical flow sweeping \ndense eroded material \ntowards the inside of \nthe bend, and leaving \nthe outside of the bend unprotected and therefore vulnerable to \naccelerated erosion, forming a positive feedback loop. \nThe associated \nlevee failures flooded the \n Mid-City facility storing the red \nstreetcars which normally run \non the Riverfront and Canal Street lines. \nChronology of Michigan lightship and lighthouses Beacons Shining in the Night, Clarke Historical Library, \nCentral, Michigan University. \nThese schools are \nalso known as \ngymnasia in English.In 1994 the \nConvention condemned the \"racist and unjust treatment\" of \nimmigrants.The old \nthree-decker forts, five in number, which formerly \nconstituted the \n principal defences of the place, and defied the Anglo-French fleets during the Crimean War, became of secondary importance.The elder then is to respond afterwards in the \n same way. \nBangalore University, Gulbarga University, Karnatak University, Kuvempu University, Mangalore University and Mysore University. \nThe difference lies only with the ability of a Turing machine to manipulate an unbounded amount of \ndata. \nEducation nominally began at the age of six. \nBorn in Costa Rica, he was raised \nin Colombia, the country of his \nfather, Armando Samper, from one year of age. \nThis allowed Russia \nto seek a solution by \nforce without risking military confrontation with other Great Powers (as had happened \nin the Crimean War of 1854 to 1856). \nIt has been \nestimated that there \nwere 22 million soccer players in the world in the early 1980s, and that number is increasing. \nCyprus \nhas a Mediterranean climate along the coast and Semi-arid climate around the capital Nicosia with long, hot and dry summers. \nIn \n1930, General Electric was compelled by antitrust charges to divest itself of RCA, which it had founded. \nThe Yivli Minare, the symbol of the city. \nThe genre of satire was common in \nRome, and satires were written by, among others, Juvenal [63] and Persius.A goal may not be scored directly from an indirect free kick. \nIn battle he has been shown capable of making his body intangible, leaving him visible but otherwise impervious \nto most forms of damage unless while executing a \ncounterattack. \nIn either case, the soul acquires a body as appropriate to \nthe \nworlds it enters.Native American and Alaska Native. \nAudio reading of the Constitution in MP3 format provided by the University of Chicago Law School.Schulze-Marmeling, Dietrich \n(2003) (in \nGerman). \nTang gathered about 100,000 soldiers, largely untrained, including Chinese \ntroops who \nhad participated in the Battle of Shanghai. \nOther independent societies are part owners of the Group.As shown in the schematic at right, the fundamental concept of TTL is \nto isolate the inputs by using the base-emitter junctions of a multiple-emitter transistor as diode switches, and to buffer the output by using a \ncommon emitter amplifier. \nThe population density was 2,684. \nAvoiding being attacked by predators. \nBulgaria has a universal, mostly \nstate-funded healthcare system. \nMatt Noveskey - sleeve art, bass and acoustic guitars, \nbacking vocals.Esteban is arrested in Mexico for suspicion of conspiracy, racketeering and tax evasion. \nThe Military Museum houses a wide range of more than 25,000 military exhibits \ndating as far back as to the \nRoman period, as well as parts of a F-117 stealth aircraft shot down \nby Yugoslav forces. \nKent State University Press, 1991.That the Italian socialist leader Dino Rondani represented Argentina in the Executive of \nthe \n Labour and Socialist International", 
    "to": [
        "hibody@csmining.org"
    ], 
    "is_spam": true, 
    "from": "\"Your #1 Medstore\" <tayizeso2909@vtr.net>", 
    "subject": "Mr. hibody, you can get your -80% coupon online ocakepix"
}