{
    "body": "-== The Best Painkillers Available in market ==- \n \nhttp://eddrefills.ru \n \nHydrocodone Watson 540 \nOxycodone HCI \nVicodin ES \nNorco \nAdderall \nK1onopin \nPhentermin \nNorco \nValiuml \nXanaxl \n \n You pay & we ship, Absolute NO question asked \n No PrescriptionNeeded (No doctor approval needed!) \n 100% deliver your order to your house \n We have been in business since 1998 \n \nThis is a rare bargain online to obtain these UNIQUE products. \nNo prior order needed. Limited supply of these hard to get pills, so be hurry! \n \nhttp://eddrefills.ru", 
    "to": [
        "<johnstebbing@csmining.org>"
    ], 
    "is_spam": true, 
    "from": "\"Mardell Georgette\" <mardell.georgettewg@kai-research.com>", 
    "subject": "Order Vicodin 30/$206, 60/$340. Buy Cheap! ell zc"
}