{
    "body": "\n\n \n \n \nFinally! \nYou've waited a long time for this! \nObtain Your University Diploma! (Phd, MBA, ect) \n\n\nHere is how to receive your University Diploma. \n\n1 - 6 4 6 - 2 1 8 - 1 2 0 0 Call Us ANYTIME! \n \n\nWhether it's a Phd or an MBA, \nthe end result is a Beautiful Diploma on your wall. \n\nThere's nothing like the feeling of getting \nthe respect of your peers and co-workers. \n\nSome things in life ARE easy. Just pick up the phone and call us today! \n\nEveryone is eligible! \n\n\n\n \n \n\n \n\n1 - 6 4 6 - 2 1 8 - 1 2 0 0 \n \n\n\n\nCall 24 hours a day, 7 days a week, \nincluding Sundays and holidays. \n\n\nFor Removal mailto:no_degree_xyz@excite.com \n\n\n\n \n\n\n\n\n", 
    "to": [
        "<Undisclosed.Recipients@dogma.slashnull.org>"
    ], 
    "is_spam": true, 
    "from": "\"Mr Schenznozt\" <akad5@excite.com>", 
    "subject": "University Diplomas"
}